README.md
setup.cfg
setup.py
chartjspy/__init__.py
chartjspy.egg-info/PKG-INFO
chartjspy.egg-info/SOURCES.txt
chartjspy.egg-info/dependency_links.txt
chartjspy.egg-info/not-zip-safe
chartjspy.egg-info/requires.txt
chartjspy.egg-info/top_level.txt