Metadata-Version: 1.1
Name: chartjspy
Version: 0.1.2
Summary: Generate Chartjs charts from python
Home-page: https://github.com/synw/chartjspy
Author: synw
Author-email: synwe@yahoo.com
License: UNKNOWN
Download-URL: https://github.com/synw/chartjspy/releases/tag/0.1.2
Keywords: charts,chartjs
Platform: UNKNOWN
Classifier: Development Status :: 3 - Alpha
Classifier: Intended Audience :: Developers
Classifier: License :: OSI Approved :: MIT License
Classifier: Programming Language :: Python :: 3.6
